messenger_api/Actions.py
messenger_api/Attachments.py
messenger_api/DefaultActionHandlers.py
messenger_api/Message.py
messenger_api/Messenger.py
messenger_api/MessengerCreateAttachmentAPI.py
messenger_api/MessengerPullParser.py
messenger_api/Person.py
messenger_api/Thread.py
messenger_api/__init__.py
messenger_api/__version__.py
messenger_api/base/Exceptions.py
messenger_api/base/MessengerAPI.py
messenger_api/base/__init__.py
messenger_api/utils/__init__.py
messenger_api/utils/universal_type_checking.py
messenger_api-0.5.1.dist-info/DESCRIPTION.rst
messenger_api-0.5.1.dist-info/METADATA
messenger_api-0.5.1.dist-info/RECORD
messenger_api-0.5.1.dist-info/WHEEL
messenger_api-0.5.1.dist-info/metadata.json
messenger_api-0.5.1.dist-info/top_level.txt
