Metadata-Version: 2.0
Name: messenger-api
Version: 0.5.1
Summary: Unofficial Facebook Messenger library for Python 2.6+ / Python 3.4+ / pypy
Home-page: https://github.com/JuniorJPDJ/messenger_api
Author: JuniorJPDJ
Author-email: juniorjpdj@interia.pl
License: LGPLv3+
Keywords: messenger facebook
Platform: UNKNOWN
Classifier: Development Status :: 3 - Alpha
Classifier: Topic :: Communications :: Chat
Classifier: License :: OSI Approved :: GNU Lesser General Public License v3 or later (LGPLv3+)
Classifier: Programming Language :: Python
Classifier: Programming Language :: Python :: 2.6
Classifier: Programming Language :: Python :: 2.7
Classifier: Programming Language :: Python :: 3
Classifier: Programming Language :: Python :: 3.4
Classifier: Programming Language :: Python :: 3.5
Classifier: Programming Language :: Python :: 3.6
Classifier: Programming Language :: Python :: Implementation :: CPython
Classifier: Programming Language :: Python :: Implementation :: PyPy
Requires-Python: >=2.6, !=3.0.*, !=3.1.*, !=3.2.*, !=3.3.*, <4
Requires-Dist: requests
